cmudict/__init__.py
cmudict/data/LICENSE
cmudict/data/README
cmudict/data/README.developer
cmudict/data/cmudict.dict
cmudict/data/cmudict.phones
cmudict/data/cmudict.symbols
cmudict/data/cmudict.vp
cmudict/py.typed
cmudict-1.1.2.dist-info/METADATA
cmudict-1.1.2.dist-info/WHEEL
cmudict-1.1.2.dist-info/licenses/LICENSE
cmudict-1.1.2.dist-info/RECORD
